[
    {
        "link": "https://geeksforgeeks.org/vector-in-cpp-stl",
        "document": ""
    },
    {
        "link": "https://en.cppreference.com/w/cpp/container/vector",
        "document": ""
    },
    {
        "link": "https://programiz.com/cpp-programming/vectors",
        "document": ""
    },
    {
        "link": "https://w3schools.com/cpp/cpp_vectors.asp",
        "document": ""
    },
    {
        "link": "https://learn.microsoft.com/en-us/cpp/standard-library/vector-class?view=msvc-170",
        "document": ""
    },
    {
        "link": "https://geeksforgeeks.org/pair-in-cpp-stl",
        "document": ""
    },
    {
        "link": "https://workat.tech/problem-solving/tutorial/cpp-stl-pair-complete-guide-ia62jqg0dszu",
        "document": ""
    },
    {
        "link": "https://stackoverflow.com/questions/11984297/creating-pair-object-c",
        "document": ""
    },
    {
        "link": "https://stackoverflow.com/questions/48945280/how-to-best-access-elements-of-stdpair",
        "document": ""
    },
    {
        "link": "https://geeksforgeeks.org/sets-of-pairs-in-c",
        "document": ""
    }
]